cafeteria/abc/__init__.py
cafeteria/abc/compat.py
cafeteria/compat.py
cafeteria/datastructs/__init__.py
cafeteria/datastructs/dict.py
cafeteria/datastructs/memory.py
cafeteria/datastructs/units/__init__.py
cafeteria/datastructs/units/data.py
cafeteria/decorators/__init__.py
cafeteria/logging/__init__.py
cafeteria/logging/trace.py
cafeteria/patterns/__init__.py
cafeteria/patterns/borg.py
cafeteria/patterns/context/__init__.py
cafeteria/patterns/dict.py
cafeteria/patterns/mixins.py
cafeteria/twisted/__init__.py
cafeteria/utilities.py
cafeteria-0.22.2.dist-info/LICENSE
cafeteria-0.22.2.dist-info/METADATA
cafeteria-0.22.2.dist-info/WHEEL
cafeteria-0.22.2.dist-info/RECORD
